Metadata-Version: 1.0
Name: gabd-probability
Version: 0.1.1
Summary: Gaussian and Binomial distributions
Home-page: UNKNOWN
Author: Biswajeet Mahato
Author-email: biswajeetm156@gmail.com
License: UNKNOWN
Platform: UNKNOWN
